dock_worker/__init__.py
dock_worker/__main__.py
dock_worker/app.py
dock_worker/cli.py
dock_worker/repo.py
dock_worker/schemas.py
dock_worker/trigger.py
dock_worker/utils.py
dock_worker/core/__init__.py
dock_worker/core/config.py
dock_worker/core/db.py
dock_worker-0.0.0.dist-info/LICENSE
dock_worker-0.0.0.dist-info/METADATA
dock_worker-0.0.0.dist-info/WHEEL
dock_worker-0.0.0.dist-info/entry_points.txt
dock_worker-0.0.0.dist-info/top_level.txt
dock_worker-0.0.0.dist-info/RECORD
