Metadata-Version: 2.2
Name: dock_worker
Version: 0.0.0
Summary: Fork Docker images between registries using GitHub Actions
Author-email: Leo Wang <leo03w@gmail.com>
Keywords: docker,github-actions,registry,cli
Classifier: Operating System :: OS Independent
Classifier: Topic :: Software Development
Classifier: Intended Audience :: Developers
Classifier: Programming Language :: Python :: 3
Classifier: Programming Language :: Python :: 3 :: Only
Classifier: Programming Language :: Python :: 3.10
Classifier: Programming Language :: Python :: 3.11
Requires-Python: >=3.10
License-File: LICENSE
Requires-Dist: requests<3.0.0,>=2.31.0
Requires-Dist: pydantic<3.0.0,>=2.4.2
Requires-Dist: loguru<1.0.0,>=0.7.2
Requires-Dist: rich<14.0.0,>=13.6.0
Requires-Dist: pydantic_settings<3.0.0,>=2.0.0
Provides-Extra: dev
Requires-Dist: pytest<8.0.0,>=7.0.0; extra == "dev"
Requires-Dist: black<23.0.0,>=22.0.0; extra == "dev"
Requires-Dist: isort<6.0.0,>=5.0.0; extra == "dev"
Requires-Dist: ruff>=0.0.256; extra == "dev"
Requires-Dist: pre-commit<4.0.0,>=3.1.1; extra == "dev"
